moralis_streams_api/__init__.py
moralis_streams_api/api_client.py
moralis_streams_api/configuration.py
moralis_streams_api/rest.py
moralis_streams_api/api/__init__.py
moralis_streams_api/api/beta_api.py
moralis_streams_api/api/evm_streams_api.py
moralis_streams_api/api/history_api.py
moralis_streams_api/api/project_api.py
moralis_streams_api/models/__init__.py
moralis_streams_api/models/abi_input.py
moralis_streams_api/models/abi_item.py
moralis_streams_api/models/abi_output.py
moralis_streams_api/models/addresses.py
moralis_streams_api/models/addresses_types_address_response.py
moralis_streams_api/models/addresses_types_addresses_add.py
moralis_streams_api/models/addresses_types_addresses_remove.py
moralis_streams_api/models/addresses_types_addresses_response.py
moralis_streams_api/models/addresses_types_delete_address_response.py
moralis_streams_api/models/advanced_options.py
moralis_streams_api/models/any_ofaddresses_types_address_response_address.py
moralis_streams_api/models/any_ofaddresses_types_addresses_add_address.py
moralis_streams_api/models/block.py
moralis_streams_api/models/history_model.py
moralis_streams_api/models/history_types_history_model.py
moralis_streams_api/models/history_types_history_response.py
moralis_streams_api/models/i_abi.py
moralis_streams_api/models/ierc20_approval.py
moralis_streams_api/models/ierc20_transfer.py
moralis_streams_api/models/inft_approval.py
moralis_streams_api/models/inft_approval_erc1155.py
moralis_streams_api/models/inft_approval_erc721.py
moralis_streams_api/models/inft_transfer.py
moralis_streams_api/models/internal_transaction.py
moralis_streams_api/models/log.py
moralis_streams_api/models/partial_streams_types_streams_model_create_.py
moralis_streams_api/models/settings_region.py
moralis_streams_api/models/settings_types_settings_model.py
moralis_streams_api/models/stats_types_stats_model.py
moralis_streams_api/models/streams_filter.py
moralis_streams_api/models/streams_model.py
moralis_streams_api-1.0.13.dist-info/LICENSE
moralis_streams_api-1.0.13.dist-info/WHEEL
moralis_streams_api-1.0.13.dist-info/METADATA
moralis_streams_api-1.0.13.dist-info/RECORD
