Metadata-Version: 2.1
Name: moralis-streams-api
Version: 1.0.13
Summary: Streams Api
Keywords: moralis streams openapi
Author-email: Matt Krueger <mkrueger@rstms.net>
Classifier: Intended Audience :: Developers
Classifier: Natural Language :: English
Classifier: Programming Language :: Python :: 3
Classifier: Programming Language :: Python :: 3.10
Requires-Dist: certifi>=14.05.14
Requires-Dist: six>=1.10
Requires-Dist: python_dateutil>=2.5.3
Requires-Dist: urllib3>=1.15.1
Requires-Dist: coverage>=4.0.3 ; extra == "dev"
Requires-Dist: nose>=1.3.7 ; extra == "dev"
Requires-Dist: pluggy>=0.3.1 ; extra == "dev"
Requires-Dist: py>=1.4.31 ; extra == "dev"
Requires-Dist: python-box ; extra == "dev"
Requires-Dist: randomize>=0.13 ; extra == "dev"
Requires-Dist: tox ; extra == "dev"
Requires-Dist: toml ; extra == "dev"
Project-URL: Home, https://github.com/rstms/moralis-streams-api
Provides-Extra: dev
